[{
  "recipient": "Jane",
  "message": "Pick up kids at school",
  "due": 1467649800000
}, {
  "recipient": "John",
  "message": "Do laundry",
  "due": 1467703800000
}, {
  "recipient": "Matthew",
  "message": "Maw lawn",
  "due": 1467738000000
}, {
  "recipient": "Jane",
  "message": "Buy milk and stuff",
  "due": 1467831600000
}, {
  "recipient": "Jane",
  "message": "Go to car mechanics",
  "due": 1467878400000
}, {
  "recipient": "Jane",
  "message": "Pick up car",
  "due": 1467910800000
}, {
  "recipient": "John",
  "message": "Prepare kids for school trip",
  "due": 1467961200000
}, {
  "recipient": "John",
  "message": "Pick up kids at school",
  "due": 1467993600000
}, {
  "recipient": "Matthew",
  "message": "Walk out dog",
  "due": 1468069200000
}]
